emoji/__init__.py
emoji/main.py
allEmoji-1.3.dist-info/LICENSE
allEmoji-1.3.dist-info/METADATA
allEmoji-1.3.dist-info/WHEEL
allEmoji-1.3.dist-info/top_level.txt
allEmoji-1.3.dist-info/RECORD
