Metadata-Version: 2.1
Name: allEmoji
Version: 1.3
Summary: Use Emojies as class attributes in Pthon
Home-page: https://github.com/Nusab19/allEmoji
Download-URL: https://github.com/Nusab19/allEmoji/releases/tag/allEmoji-1.3
Author: Nusab Taha
Author-email: nusabtaha33@gmail.com
License: MIT
Keywords: Emoji,allEmoji,pyEmoji
Classifier: Development Status :: 5 - Production/Stable
Classifier: Intended Audience :: Developers
Classifier: Topic :: Education
Classifier: License :: OSI Approved :: MIT License
Classifier: Programming Language :: Python :: 3.6
Classifier: Programming Language :: Python :: 3.9
Classifier: Programming Language :: Python :: 3.10
Requires-Python: >=3.6
License-File: LICENSE
